infra_core/__init__.py
infra_core/asset_client.py
infra_core/azure_storage.py
infra_core/fs_utils.py
infra_core/http.py
infra_core/http_async.py
infra_core/http_utils.py
infra_core/logging_utils.py
infra_core/polling.py
infra_core/py.typed
infra_core/retry.py
infra_core/task_runtime.py
infra_core/azure/__init__.py
infra_core/azure/client.py
infra_core/azure/exceptions.py
infra_core/azure/function_cli.py
infra_core/azure/function_http.py
infra_core/azure/job_store.py
infra_core/azure/monitoring.py
infra_core/azure/run_service.py
infra_core/azure/run_storage.py
infra_core/azure/storage.py
infra_core-0.7.3.dist-info/licenses/LICENSE
infra_core-0.7.3.dist-info/METADATA
infra_core-0.7.3.dist-info/WHEEL
infra_core-0.7.3.dist-info/top_level.txt
infra_core-0.7.3.dist-info/RECORD
