Metadata-Version: 2.4
Name: infra-core
Version: 0.7.3
Summary: Shared HTTP, storage, and runtime helpers for automation services.
Author-email: Infra Core maintainers <infra-core@example.com>
Maintainer-email: Infra Core maintainers <infra-core@example.com>
License-Expression: MIT
Project-URL: Homepage, https://github.com/pj-ms/infra-core
Project-URL: Repository, https://github.com/pj-ms/infra-core
Project-URL: Issues, https://github.com/pj-ms/infra-core/issues
Keywords: http,storage,azure,async,infrastructure
Classifier: Development Status :: 3 - Alpha
Classifier: Intended Audience :: Developers
Classifier: Programming Language :: Python :: 3
Classifier: Programming Language :: Python :: 3.10
Classifier: Programming Language :: Python :: 3.11
Classifier: Programming Language :: Python :: 3.12
Classifier: Programming Language :: Python :: 3.13
Classifier: Topic :: Software Development :: Libraries
Classifier: Typing :: Typed
Requires-Python: >=3.10
License-File: LICENSE
Requires-Dist: requests<3.0,>=2.31.0
Requires-Dist: httpx<1.0,>=0.27.0
Requires-Dist: tenacity<9.0,>=8.2.2
Provides-Extra: azure
Requires-Dist: azure-core<2.0,>=1.29; extra == "azure"
Requires-Dist: azure-storage-blob<13.0,>=12.12; extra == "azure"
Requires-Dist: azure-identity<2.0,>=1.17; extra == "azure"
Requires-Dist: azure-data-tables<13.0,>=12.5.0; extra == "azure"
Provides-Extra: dev
Requires-Dist: pytest>=8.0; extra == "dev"
Requires-Dist: pytest-asyncio>=0.23; extra == "dev"
Requires-Dist: pytest-cov>=4.0; extra == "dev"
Requires-Dist: pytest-httpx>=0.30; extra == "dev"
Requires-Dist: respx>=0.20; extra == "dev"
Requires-Dist: mypy>=1.8; extra == "dev"
Requires-Dist: ruff>=0.1; extra == "dev"
Requires-Dist: pre-commit>=3.6; extra == "dev"
Requires-Dist: bump-my-version>=0.26.0; extra == "dev"
Dynamic: license-file
